{
    "Conclusion": {
        "NumSprinkler": 2753,
        "NumFireCompart": 5,
        "FireCompartArea": 19147.152,
        "NumMainBuilding": 1,
        "MainBuildingArea": 1261.591,
        "NumBarrier": 140,
        "NumBlock": 371,
        "NumBlockSolvedByParallelogram": 0,
        "NumBlockSolvedByRectangle": 0,
        "NumBlockSolvedByPolygon": 0,
        "NumBlockFailed": 0,
        "SolvingTime": 0,
        "InteriorUniformityMetric": 1519000,
        "ExteriorUniformityMetric": 433976,
        "AlignedMetric": [
            2039,
            288
        ],
        "CoverageRate": 0.9670288897804401
    },
    "Detail": [
        {
            "FireCompartName": "fire_compart 100",
            "NumSprinkler": 567,
            "Area": 3880.784,
            "NumBarrier": 30,
            "NumBlock": 73
        },
        {
            "FireCompartName": "fire_compart 102",
            "NumSprinkler": 551,
            "Area": 3886.171,
            "NumBarrier": 16,
            "NumBlock": 77
        },
        {
            "FireCompartName": "fire_compart 103",
            "NumSprinkler": 458,
            "Area": 3075.404,
            "NumBarrier": 25,
            "NumBlock": 59
        },
        {
            "FireCompartName": "fire_compart 104",
            "NumSprinkler": 681,
            "Area": 4896.986,
            "NumBarrier": 33,
            "NumBlock": 90
        },
        {
            "FireCompartName": "fire_compart 105",
            "NumSprinkler": 496,
            "Area": 3407.808,
            "NumBarrier": 36,
            "NumBlock": 72
        }
    ]
}